mautrix_hangouts/__init__.py
mautrix_hangouts/__main__.py
mautrix_hangouts/config.py
mautrix_hangouts/context.py
mautrix_hangouts/example-config.yaml
mautrix_hangouts/get_version.py
mautrix_hangouts/matrix.py
mautrix_hangouts/portal.py
mautrix_hangouts/puppet.py
mautrix_hangouts/user.py
mautrix_hangouts/version.py
mautrix_hangouts/commands/__init__.py
mautrix_hangouts/commands/auth.py
mautrix_hangouts/commands/typehint.py
mautrix_hangouts/db/__init__.py
mautrix_hangouts/db/message.py
mautrix_hangouts/db/portal.py
mautrix_hangouts/db/puppet.py
mautrix_hangouts/db/user.py
mautrix_hangouts/util/__init__.py
mautrix_hangouts/util/color_log.py
mautrix_hangouts/util/hangups_try_auth.py
mautrix_hangouts/web/__init__.py
mautrix_hangouts/web/auth.py
mautrix_hangouts/web/static/favicon.png
mautrix_hangouts/web/static/loader.css
mautrix_hangouts/web/static/login-redirect.html
mautrix_hangouts/web/static/login.css
mautrix_hangouts/web/static/login.html
mautrix_hangouts/web/static/login.js
mautrix_hangouts-0.1.4.data/data/alembic.ini
mautrix_hangouts-0.1.4.data/data/example-config.yaml
mautrix_hangouts-0.1.4.data/data/alembic/env.py
mautrix_hangouts-0.1.4.data/data/alembic/versions/33078cd14618_add_double_puppet_base_url_to_puppet_.py
mautrix_hangouts-0.1.4.data/data/alembic/versions/41712fc6d14b_add_user_portal_puppet_mappings_to_db.py
mautrix_hangouts-0.1.4.data/data/alembic/versions/4567a7c4de97_switch_to_mautrix_python_crypto.py
mautrix_hangouts-0.1.4.data/data/alembic/versions/52cd44bea796_stop_using_size_limited_string_fields.py
mautrix_hangouts-0.1.4.data/data/alembic/versions/63ea9db2aa00_add_receiver_and_index_fields_to_.py
mautrix_hangouts-0.1.4.data/data/alembic/versions/7d9a9a4d50d7_add_timestamp_to_messages.py
mautrix_hangouts-0.1.4.data/data/alembic/versions/ab5435bd192e_add_bridge_notice_room_column_for_users.py
mautrix_hangouts-0.1.4.data/data/alembic/versions/ba113d486f7f_store_custom_puppet_next_batch_in_.py
mautrix_hangouts-0.1.4.dist-info/LICENSE
mautrix_hangouts-0.1.4.dist-info/METADATA
mautrix_hangouts-0.1.4.dist-info/WHEEL
mautrix_hangouts-0.1.4.dist-info/top_level.txt
mautrix_hangouts-0.1.4.dist-info/RECORD
